{
  "kind": "singleType",
  "collectionName": "data_products",
  "info": {
    "singularName": "data-product",
    "pluralName": "data-products",
    "displayName": "data_product",
    "description": ""
  },
  "options": {
    "draftAndPublish": true
  },
  "pluginOptions": {},
  "attributes": {
    "data_products_hero_title": {
      "type": "string"
    },
    "data_products_hero_description_top": {
      "type": "customField",
      "options": {
        "preset": "toolbar"
      },
      "customField": "plugin::ckeditor5.CKEditor"
    },
    "data_products_hero_description_bottom": {
      "type": "customField",
      "options": {
        "preset": "toolbar"
      },
      "customField": "plugin::ckeditor5.CKEditor"
    },
    "data_products_hero_img": {
      "type": "media",
      "multiple": false,
      "required": false,
      "allowedTypes": [
        "images",
        "files",
        "videos",
        "audios"
      ]
    },
    "data_products_products_titl": {
      "type": "string"
    },
    "products": {
      "type": "component",
      "repeatable": true,
      "component": "data-products.data-products-products-card"
    },
    "data_products_process_title": {
      "type": "string"
    },
    "data_products_process_description": {
      "type": "customField",
      "options": {
        "preset": "toolbar"
      },
      "customField": "plugin::ckeditor5.CKEditor"
    },
    "testimonials": {
      "type": "component",
      "repeatable": true,
      "component": "homepage.testimonials"
    },
    "data_product_testimonial_title": {
      "type": "string"
    },
    "hero_description_bottom2": {
      "type": "text"
    },
    "sectors": {
      "type": "component",
      "repeatable": true,
      "component": "general.find-more"
    },
    "our_process_title": {
      "type": "string"
    },
    "our_process_description": {
      "type": "customField",
      "options": {
        "preset": "toolbar"
      },
      "customField": "plugin::ckeditor5.CKEditor"
    },
    "discovery_title": {
      "type": "string"
    },
    "discovery_description": {
      "type": "text"
    },
    "discovery_images": {
      "type": "media",
      "multiple": true,
      "required": false,
      "allowedTypes": [
        "images",
        "files",
        "videos",
        "audios"
      ]
    },
    "scope_title": {
      "type": "string"
    },
    "scope_description": {
      "type": "text"
    },
    "scope_img1": {
      "type": "media",
      "multiple": false,
      "required": false,
      "allowedTypes": [
        "images",
        "files",
        "videos",
        "audios"
      ]
    },
    "scope_img2": {
      "type": "media",
      "multiple": false,
      "required": false,
      "allowedTypes": [
        "images",
        "files",
        "videos",
        "audios"
      ]
    },
    "scope_img3": {
      "type": "media",
      "multiple": true,
      "required": false,
      "allowedTypes": [
        "images",
        "files",
        "videos",
        "audios"
      ]
    },
    "excerpt": {
      "type": "customField",
      "options": {
        "preset": "toolbar"
      },
      "customField": "plugin::ckeditor5.CKEditor"
    }
  }
}
